<package>
  <description brief="JRL mathematical tools">

    Basic mathematical tools providings small vectors, matrices
    and angles classes.

  </description>
  <author>See package AUTHORS file.</author>
  <license>LGPL</license>
  <review status="experimental" notes=""/>
  <url>http://ros.org/wiki/jrl-mathtools</url>

  <export>
    <rosdoc
       external=
       "http://jrl-umi3218.github.com/jrl-mathtools/doxygen/HEAD/index.html" />
  </export>
  <rosdep name="git"/>
  <rosdep name="boost"/>
  <versioncontrol type="git"
		  url="git://github.com/jrl-umi3218/jrl-mathtools.git"/>
</package>
